muti_thread/__init__.py
muti_thread/muti_thread.pyd
muti_thread/muti_thread.so
muti_thread/muti_thread_test.py
muti_thread-1.1.10.dist-info/METADATA
muti_thread-1.1.10.dist-info/WHEEL
muti_thread-1.1.10.dist-info/top_level.txt
muti_thread-1.1.10.dist-info/RECORD
