Metadata-Version: 2.1
Name: muti-thread
Version: 1.1.10
Summary: muti_thread是多线程并发库
Home-page: https://github.com/passion765
Author: tk
Author-email: 462304@qq.com
License: UNKNOWN
Keywords: muti-thread,threading,thread,muti_thread,threads
Platform: Linux
Platform: Windows
Classifier: Development Status :: 3 - Alpha
Classifier: Intended Audience :: Developers
Classifier: Topic :: Software Development :: Build Tools
Classifier: License :: OSI Approved :: MIT License
Classifier: Programming Language :: Python :: 3.6
Classifier: Operating System :: OS Independent
Requires-Python: >=3.6
